pydbk/__init__.py
pydbk/pydbk.py
pydbk/pydbk_cli.py
pydbk-1.0.0.dist-info/LICENSE
pydbk-1.0.0.dist-info/METADATA
pydbk-1.0.0.dist-info/WHEEL
pydbk-1.0.0.dist-info/entry_points.txt
pydbk-1.0.0.dist-info/top_level.txt
pydbk-1.0.0.dist-info/RECORD
