Metadata-Version: 2.1
Name: pydbk
Version: 1.0.0
Summary: A Python tool to extract .dbk archives.
Home-page: https://github.com/BenPortner/pydbk
Author: Benjamin W. Portner
Author-email: "Benjamin W. Portner" <benwportner@gmail.com>
License: GNU AFFERO GENERAL PUBLIC LICENSE
Project-URL: Homepage, https://github.com/BenPortner/pydbk
Project-URL: Bug Tracker, https://github.com/BenPortner/pydbk/issues
Classifier: Development Status :: 4 - Beta
Classifier: Intended Audience :: End Users/Desktop
Classifier: Intended Audience :: Developers
Classifier: Programming Language :: Python :: 3.10
Classifier: Programming Language :: Python :: 3.11
Classifier: Operating System :: OS Independent
Requires-Python: >=3.10
License-File: LICENSE
